dnssec_cli-1.1.0.dist-info/licenses/LICENSE
dnssec_tool/__init__.py
dnssec_tool/analyzer.py
dnssec_tool/cli.py
dnssec_tool/dig.py
dnssec_tool/parser.py
dnssec_tool/pcap.py
dnssec_tool/resolver_chain.py
dnssec_tool/validator.py
dnssec_cli-1.1.0.dist-info/METADATA
dnssec_cli-1.1.0.dist-info/WHEEL
dnssec_cli-1.1.0.dist-info/entry_points.txt
dnssec_cli-1.1.0.dist-info/top_level.txt
dnssec_cli-1.1.0.dist-info/RECORD
