Metadata-Version: 2.4
Name: dnssec-cli
Version: 1.1.0
Summary: A professional CLI toolkit for DNSSEC scanning and DNS forensic analysis.
Home-page: https://github.com/tuusuario/dnssec-toolkit
Author-email: Julio Briones <julio.brionesw@gmail.com>
Project-URL: Homepage, https://github.com/julesbw/dnssec-cli
Project-URL: Repository, https://github.com/julesbw/dnssec-cli
Project-URL: Issues, https://github.com/julesbw/dnssec-cli/issues
Requires-Python: >=3.8
License-File: LICENSE
Requires-Dist: click
Requires-Dist: rich
Requires-Dist: pyshark
Requires-Dist: dnspython
Dynamic: home-page
Dynamic: license-file
